{
  "type": "https://tools.ietf.org/html/rfc9110#section-15.6.1",
  "title": "A possible object cycle was detected. This can either be due to a cycle or if the object depth is larger than the maximum allowed depth of 32. Consider using ReferenceHandler.Preserve on JsonSerializerOptions to support cycles. Path: $.Parent.Terms.Parent.Terms.Parent.Terms.Parent.Terms.Parent.Terms.Parent.Terms.Parent.Terms.Parent.Terms.Parent.Terms.Parent.Terms.",
  "status": 500,
  "detail": "A possible object cycle was detected. This can either be due to a cycle or if the object depth is larger than the maximum allowed depth of 32. Consider using ReferenceHandler.Preserve on JsonSerializerOptions to support cycles. Path: $.Parent.Terms.Parent.Terms.Parent.Terms.Parent.Terms.Parent.Terms.Parent.Terms.Parent.Terms.Parent.Terms.Parent.Terms.Parent.Terms.",
  "traceId": "00-69008cecb86826f1200fb3f45963c142-ed8424be4c8480fd-00"
}